spit/LOOCV.py
spit/__init__.py
spit/cluster_samples.py
spit/confounding_analysis.py
spit/dtu_detection.py
spit/filter_and_simulate_tx_counts.py
spit/filter_and_transform_tx_counts.py
spit/get_p_cutoff.py
spit/import_infreps.py
spit/plot_spit_charts.py
spit/run_spit.py
spit/run_spit_search_params.py
spit/simulate_dtu.py
spit/simulate_exps.py
spit/spit_test.py
spit/transform_tx_counts_to_ifs.py
spit-2.0.4.dist-info/LICENSE
spit-2.0.4.dist-info/METADATA
spit-2.0.4.dist-info/WHEEL
spit-2.0.4.dist-info/entry_points.txt
spit-2.0.4.dist-info/top_level.txt
spit-2.0.4.dist-info/RECORD
