Metadata-Version: 2.1
Name: spit
Version: 2.0.4
Summary: Comprehensive Python package for detecting differential transcript usage (DTU) in RNA-seq data.
Requires-Python: >=3.9
License-File: LICENSE
Requires-Dist: matplotlib >=3.4.3
Requires-Dist: matplotlib-venn >=0.11.6
Requires-Dist: numpy >=1.20.3
Requires-Dist: pandas >=1.3.4
Requires-Dist: scikit-learn >=1.1.1
Requires-Dist: scipy >=1.11.1
Requires-Dist: seaborn >=0.11.2
Requires-Dist: tqdm >=4.62.3
